softrag/__init__.py
softrag/softrag.py
softrag-0.1.4.dist-info/licenses/LICENSE
softrag-0.1.4.dist-info/METADATA
softrag-0.1.4.dist-info/WHEEL
softrag-0.1.4.dist-info/top_level.txt
softrag-0.1.4.dist-info/RECORD
