Metadata-Version: 2.4
Name: softrag
Version: 0.1.4
Summary: Minimal local-first Retrieval-Augmented Generation (RAG) library using SQLite with sqlite-vec
Author-email: SoftRAG Team <contato@softrag.com>
License: MIT
Project-URL: Homepage, https://github.com/JulioPeixoto/softrag
Project-URL: Issues , https://github.com/JulioPeixoto/softrag/issues
Classifier: Programming Language :: Python :: 3
Classifier: License :: OSI Approved :: MIT License
Classifier: Operating System :: OS Independent
Classifier: Topic :: Scientific/Engineering :: Artificial Intelligence
Classifier: Intended Audience :: Developers
Requires-Python: >=3.12
License-File: LICENSE
Requires-Dist: docx2txt>=0.9
Requires-Dist: langchain-text-splitters>=0.3.8
Requires-Dist: llama-index-readers-file>=0.4.7
Requires-Dist: pymupdf>=1.25.5
Requires-Dist: six>=1.16.0
Requires-Dist: sqlite-vec>=0.1.6
Requires-Dist: trafilatura>=2.0.0
Dynamic: license-file
